mailblog/__init__.py
mailblog/blog.py
mailblog/blog_test.py
mailblog/trivial_orm.py
mailblog/templates/__init__.py
mailblog/templates/base.html
mailblog/templates/index.html
mailblog/templates/main.html
mailblog/templates/new-feed.xml
mailblog/templates/page.html
mailblog/templates/user-feed.xml
mailblog-0.0.2.dist-info/LICENSE
mailblog-0.0.2.dist-info/METADATA
mailblog-0.0.2.dist-info/WHEEL
mailblog-0.0.2.dist-info/entry_points.txt
mailblog-0.0.2.dist-info/top_level.txt
mailblog-0.0.2.dist-info/RECORD
