Metadata-Version: 2.1
Name: mailblog
Version: 0.0.2
Summary: blog posts from emails
Home-page: https://github.com/ihaywood3/mailblog
Author: Ian Haywood
Author-email: ian@haywood.id.au
License: GNU GPL 3
Project-URL: Bug Tracker, https://github.com/ihaywood3/mailblog/issues
Keywords: blog,email
Platform: UNKNOWN
Classifier: Development Status :: 4 - Beta
Classifier: Environment :: Console
Classifier: Intended Audience :: Developers
Classifier: License :: OSI Approved :: GNU General Public License v3 or later (GPLv3+)
Classifier: Operating System :: OS Independent
Classifier: Programming Language :: Python :: 3
Classifier: Topic :: Communications :: Email
Classifier: Topic :: Internet :: WWW/HTTP :: Dynamic Content :: News/Diary
License-File: LICENSE
Requires-Dist: mako
Requires-Dist: markdown
